xontrib/mise.py
xontrib_mise-0.0.6.dist-info/LICENSE
xontrib_mise-0.0.6.dist-info/METADATA
xontrib_mise-0.0.6.dist-info/WHEEL
xontrib_mise-0.0.6.dist-info/RECORD
