Metadata-Version: 2.3
Name: xontrib-mise
Version: 0.0.6
Summary: Initializes mise (polyglot asdf-like runtime manager)
License: MIT
Keywords: xontrib,xonsh
Author: Evgeny
Author-email: es.bugzilla@gmail.com
Requires-Python: >=3.9,<4.0
Classifier: Intended Audience :: Developers
Classifier: License :: OSI Approved :: MIT License
Classifier: Natural Language :: English
Classifier: Operating System :: OS Independent
Classifier: Programming Language :: Python :: 3
Classifier: Programming Language :: Python :: 3.9
Classifier: Programming Language :: Python :: 3.10
Classifier: Programming Language :: Python :: 3.11
Classifier: Programming Language :: Python :: 3.12
Classifier: Programming Language :: Python :: 3.13
Classifier: Topic :: System :: Shells
Classifier: Topic :: System :: System Shells
Classifier: Topic :: Terminals
Requires-Dist: xonsh (>=0.18.2)
Project-URL: Code, https://github.com/eugenesvk/xontrib-mise
Project-URL: Documentation, https://github.com/eugenesvk/xontrib-mise/blob/master/README.md
Project-URL: Homepage, https://github.com/eugenesvk/xontrib-mise
Project-URL: Issue tracker, https://github.com/eugenesvk/xontrib-mise/issues
Project-URL: Repository, https://github.com/eugenesvk/xontrib-mise
